<Map><Tiles><Tile><XPos>0.0</XPos><YPos>12.0</YPos><Street>WestEast</Street></Tile><Tile><XPos>1.0</XPos><YPos>12.0</YPos><Street>WestEast</Street></Tile><Tile><XPos>2.0</XPos><YPos>12.0</YPos><Street>WestEast</Street></Tile><Tile><XPos>3.0</XPos><YPos>7.0</YPos><Street>BendES</Street></Tile><Tile><XPos>3.0</XPos><YPos>8.0</YPos><Street>SouthNorth</Street></Tile><Tile><XPos>3.0</XPos><YPos>9.0</YPos><Street>SouthNorth</Street></Tile><Tile><XPos>3.0</XPos><YPos>10.0</YPos><Street>SouthNorth</Street></Tile><Tile><XPos>3.0</XPos><YPos>11.0</YPos><Street>SouthNorth</Street></Tile><Tile><XPos>3.0</XPos><YPos>12.0</YPos><Street>Intersection</Street></Tile><Tile><XPos>3.0</XPos><YPos>13.0</YPos><Street>SouthNorth</Street></Tile><Tile><XPos>3.0</XPos><YPos>14.0</YPos><Street>SouthNorth</Street></Tile><Tile><XPos>3.0</XPos><YPos>15.0</YPos><Street>SouthNorth</Street></Tile><Tile><XPos>3.0</XPos><YPos>16.0</YPos><Street>SouthNorth</Street></Tile><Tile><XPos>3.0</XPos><YPos>17.0</YPos><Street>SouthNorth</Street></Tile><Tile><XPos>3.0</XPos><YPos>18.0</YPos><Street>SouthNorth</Street></Tile><Tile><XPos>3.0</XPos><YPos>19.0</YPos><Street>SouthNorth</Street></Tile><Tile><XPos>4.0</XPos><YPos>7.0</YPos><Street>WestEast</Street></Tile><Tile><XPos>4.0</XPos><YPos>12.0</YPos><Street>WestEast</Street></Tile><Tile><XPos>5.0</XPos><YPos>5.0</YPos><Street>BendES</Street></Tile><Tile><XPos>5.0</XPos><YPos>6.0</YPos><Street>SouthNorth</Street></Tile><Tile><XPos>5.0</XPos><YPos>7.0</YPos><Street>TIntersectionNoSouth</Street></Tile><Tile><XPos>5.0</XPos><YPos>12.0</YPos><Street>WestEast</Street></Tile><Tile><XPos>6.0</XPos><YPos>5.0</YPos><Street>WestEast</Street></Tile><Tile><XPos>6.0</XPos><YPos>7.0</YPos><Street>WestEast</Street></Tile><Tile><XPos>6.0</XPos><YPos>12.0</YPos><Street>WestEast</Street></Tile><Tile><XPos>7.0</XPos><YPos>5.0</YPos><Street>WestEast</Street></Tile><Tile><XPos>7.0</XPos><YPos>7.0</YPos><Street>BendSW</Street></Tile><Tile><XPos>7.0</XPos><YPos>8.0</YPos><Street>SouthNorth</Street></Tile><Tile><XPos>7.0</XPos><YPos>9.0</YPos><Street>SouthNorth</Street></Tile><Tile><XPos>7.0</XPos><YPos>10.0</YPos><Street>SouthNorth</Street></Tile><Tile><XPos>7.0</XPos><YPos>11.0</YPos><Street>SouthNorth</Street></Tile><Tile><XPos>7.0</XPos><YPos>12.0</YPos><Street>Bridge</Street></Tile><Tile><XPos>7.0</XPos><YPos>13.0</YPos><Street>BendEN</Street></Tile><Tile><XPos>8.0</XPos><YPos>5.0</YPos><Street>WestEast</Street></Tile><Tile><XPos>8.0</XPos><YPos>12.0</YPos><Street>TIntersectionNoNorth</Street></Tile><Tile><XPos>8.0</XPos><YPos>13.0</YPos><Street>BendWN</Street></Tile><Tile><XPos>9.0</XPos><YPos>5.0</YPos><Street>WestEast</Street></Tile><Tile><XPos>9.0</XPos><YPos>12.0</YPos><Street>WestEast</Street></Tile><Tile><XPos>10.0</XPos><YPos>5.0</YPos><Street>WestEast</Street></Tile><Tile><XPos>10.0</XPos><YPos>12.0</YPos><Street>WestEast</Street></Tile><Tile><XPos>11.0</XPos><YPos>5.0</YPos><Street>WestEast</Street></Tile><Tile><XPos>11.0</XPos><YPos>12.0</YPos><Street>WestEast</Street></Tile><Tile><XPos>12.0</XPos><YPos>5.0</YPos><Street>WestEast</Street></Tile><Tile><XPos>12.0</XPos><YPos>12.0</YPos><Street>WestEast</Street></Tile><Tile><XPos>13.0</XPos><YPos>5.0</YPos><Street>WestEast</Street></Tile><Tile><XPos>13.0</XPos><YPos>12.0</YPos><Street>WestEast</Street></Tile><Tile><XPos>14.0</XPos><YPos>5.0</YPos><Street>WestEast</Street></Tile><Tile><XPos>14.0</XPos><YPos>12.0</YPos><Street>WestEast</Street></Tile><Tile><XPos>15.0</XPos><YPos>5.0</YPos><Street>WestEast</Street></Tile><Tile><XPos>15.0</XPos><YPos>12.0</YPos><Street>WestEast</Street></Tile><Tile><XPos>16.0</XPos><YPos>5.0</YPos><Street>WestEast</Street></Tile><Tile><XPos>16.0</XPos><YPos>6.0</YPos><Street>DeleteStreet</Street></Tile><Tile><XPos>16.0</XPos><YPos>12.0</YPos><Street>WestEast</Street></Tile><Tile><XPos>17.0</XPos><YPos>0.0</YPos><Street>BendES</Street></Tile><Tile><XPos>17.0</XPos><YPos>1.0</YPos><Street>SouthNorth</Street></Tile><Tile><XPos>17.0</XPos><YPos>2.0</YPos><Street>SouthNorth</Street></Tile><Tile><XPos>17.0</XPos><YPos>3.0</YPos><Street>SouthNorth</Street></Tile><Tile><XPos>17.0</XPos><YPos>4.0</YPos><Street>SouthNorth</Street></Tile><Tile><XPos>17.0</XPos><YPos>5.0</YPos><Street>TIntersectionNoEast</Street></Tile><Tile><XPos>17.0</XPos><YPos>6.0</YPos><Street>SouthNorth</Street></Tile><Tile><XPos>17.0</XPos><YPos>7.0</YPos><Street>SouthNorth</Street></Tile><Tile><XPos>17.0</XPos><YPos>8.0</YPos><Street>SouthNorth</Street></Tile><Tile><XPos>17.0</XPos><YPos>9.0</YPos><Street>SouthNorth</Street></Tile><Tile><XPos>17.0</XPos><YPos>10.0</YPos><Street>SouthNorth</Street></Tile><Tile><XPos>17.0</XPos><YPos>11.0</YPos><Street>SouthNorth</Street></Tile><Tile><XPos>17.0</XPos><YPos>12.0</YPos><Street>TIntersectionNoSouth</Street></Tile><Tile><XPos>18.0</XPos><YPos>0.0</YPos><Street>WestEast</Street></Tile><Tile><XPos>18.0</XPos><YPos>10.0</YPos><Street>DeleteStreet</Street></Tile><Tile><XPos>18.0</XPos><YPos>12.0</YPos><Street>WestEast</Street></Tile><Tile><XPos>19.0</XPos><YPos>0.0</YPos><Street>WestEast</Street></Tile><Tile><XPos>19.0</XPos><YPos>12.0</YPos><Street>WestEast</Street></Tile><Tile><XPos>20.0</XPos><YPos>0.0</YPos><Street>WestEast</Street></Tile><Tile><XPos>20.0</XPos><YPos>12.0</YPos><Street>WestEast</Street></Tile><Tile><XPos>21.0</XPos><YPos>0.0</YPos><Street>WestEast</Street></Tile><Tile><XPos>21.0</XPos><YPos>12.0</YPos><Street>WestEast</Street></Tile><Tile><XPos>22.0</XPos><YPos>0.0</YPos><Street>WestEast</Street></Tile><Tile><XPos>22.0</XPos><YPos>12.0</YPos><Street>WestEast</Street></Tile><Tile><XPos>23.0</XPos><YPos>0.0</YPos><Street>WestEast</Street></Tile><Tile><XPos>23.0</XPos><YPos>12.0</YPos><Street>WestEast</Street></Tile><Tile><XPos>24.0</XPos><YPos>0.0</YPos><Street>WestEast</Street></Tile><Tile><XPos>24.0</XPos><YPos>12.0</YPos><Street>WestEast</Street></Tile><Tile><XPos>25.0</XPos><YPos>0.0</YPos><Street>WestEast</Street></Tile><Tile><XPos>25.0</XPos><YPos>12.0</YPos><Street>WestEast</Street></Tile><Tile><XPos>26.0</XPos><YPos>0.0</YPos><Street>WestEast</Street></Tile><Tile><XPos>26.0</XPos><YPos>12.0</YPos><Street>WestEast</Street></Tile><Tile><XPos>26.0</XPos><YPos>13.0</YPos><Street>DeleteStreet</Street></Tile><Tile><XPos>27.0</XPos><YPos>0.0</YPos><Street>WestEast</Street></Tile><Tile><XPos>27.0</XPos><YPos>12.0</YPos><Street>WestEast</Street></Tile><Tile><XPos>27.0</XPos><YPos>13.0</YPos><Street>DeleteStreet</Street></Tile><Tile><XPos>28.0</XPos><YPos>0.0</YPos><Street>BendSW</Street></Tile><Tile><XPos>28.0</XPos><YPos>1.0</YPos><Street>SouthNorth</Street></Tile><Tile><XPos>28.0</XPos><YPos>2.0</YPos><Street>SouthNorth</Street></Tile><Tile><XPos>28.0</XPos><YPos>3.0</YPos><Street>SouthNorth</Street></Tile><Tile><XPos>28.0</XPos><YPos>4.0</YPos><Street>SouthNorth</Street></Tile><Tile><XPos>28.0</XPos><YPos>5.0</YPos><Street>SouthNorth</Street></Tile><Tile><XPos>28.0</XPos><YPos>6.0</YPos><Street>TIntersectionNoWest</Street></Tile><Tile><XPos>28.0</XPos><YPos>7.0</YPos><Street>SouthNorth</Street></Tile><Tile><XPos>28.0</XPos><YPos>8.0</YPos><Street>SouthNorth</Street></Tile><Tile><XPos>28.0</XPos><YPos>9.0</YPos><Street>SouthNorth</Street></Tile><Tile><XPos>28.0</XPos><YPos>10.0</YPos><Street>SouthNorth</Street></Tile><Tile><XPos>28.0</XPos><YPos>11.0</YPos><Street>SouthNorth</Street></Tile><Tile><XPos>28.0</XPos><YPos>12.0</YPos><Street>Intersection</Street></Tile><Tile><XPos>28.0</XPos><YPos>13.0</YPos><Street>SouthNorth</Street></Tile><Tile><XPos>28.0</XPos><YPos>14.0</YPos><Street>SouthNorth</Street></Tile><Tile><XPos>28.0</XPos><YPos>15.0</YPos><Street>SouthNorth</Street></Tile><Tile><XPos>28.0</XPos><YPos>16.0</YPos><Street>SouthNorth</Street></Tile><Tile><XPos>28.0</XPos><YPos>17.0</YPos><Street>SouthNorth</Street></Tile><Tile><XPos>28.0</XPos><YPos>18.0</YPos><Street>SouthNorth</Street></Tile><Tile><XPos>28.0</XPos><YPos>19.0</YPos><Street>SouthNorth</Street></Tile><Tile><XPos>29.0</XPos><YPos>6.0</YPos><Street>WestEast</Street></Tile><Tile><XPos>29.0</XPos><YPos>12.0</YPos><Street>WestEast</Street></Tile><Tile><XPos>29.0</XPos><YPos>19.0</YPos><Street>DeleteStreet</Street></Tile><Tile><XPos>30.0</XPos><YPos>6.0</YPos><Street>WestEast</Street></Tile><Tile><XPos>30.0</XPos><YPos>12.0</YPos><Street>WestEast</Street></Tile><Tile><XPos>31.0</XPos><YPos>6.0</YPos><Street>WestEast</Street></Tile><Tile><XPos>31.0</XPos><YPos>12.0</YPos><Street>WestEast</Street></Tile><Tile><XPos>32.0</XPos><YPos>6.0</YPos><Street>TIntersectionNoNorth</Street></Tile><Tile><XPos>32.0</XPos><YPos>7.0</YPos><Street>SouthNorth</Street></Tile><Tile><XPos>32.0</XPos><YPos>8.0</YPos><Street>SouthNorth</Street></Tile><Tile><XPos>32.0</XPos><YPos>9.0</YPos><Street>SouthNorth</Street></Tile><Tile><XPos>32.0</XPos><YPos>10.0</YPos><Street>SouthNorth</Street></Tile><Tile><XPos>32.0</XPos><YPos>11.0</YPos><Street>SouthNorth</Street></Tile><Tile><XPos>32.0</XPos><YPos>12.0</YPos><Street>TIntersectionNoSouth</Street></Tile><Tile><XPos>32.0</XPos><YPos>13.0</YPos><Street>DeleteStreet</Street></Tile><Tile><XPos>32.0</XPos><YPos>14.0</YPos><Street>DeleteStreet</Street></Tile><Tile><XPos>32.0</XPos><YPos>15.0</YPos><Street>DeleteStreet</Street></Tile><Tile><XPos>32.0</XPos><YPos>16.0</YPos><Street>DeleteStreet</Street></Tile><Tile><XPos>32.0</XPos><YPos>17.0</YPos><Street>DeleteStreet</Street></Tile><Tile><XPos>32.0</XPos><YPos>18.0</YPos><Street>DeleteStreet</Street></Tile><Tile><XPos>32.0</XPos><YPos>19.0</YPos><Street>DeleteStreet</Street></Tile><Tile><XPos>33.0</XPos><YPos>6.0</YPos><Street>WestEast</Street></Tile><Tile><XPos>33.0</XPos><YPos>12.0</YPos><Street>WestEast</Street></Tile><Tile><XPos>33.0</XPos><YPos>13.0</YPos><Street>DeleteStreet</Street></Tile><Tile><XPos>33.0</XPos><YPos>14.0</YPos><Street>DeleteStreet</Street></Tile><Tile><XPos>33.0</XPos><YPos>15.0</YPos><Street>DeleteStreet</Street></Tile><Tile><XPos>34.0</XPos><YPos>6.0</YPos><Street>WestEast</Street></Tile><Tile><XPos>34.0</XPos><YPos>12.0</YPos><Street>WestEastEntry</Street></Tile></Tiles>
<Config><getWidth>700.0</getWidth><getHeight>400.0</getHeight><getTileSize>20.0</getTileSize><isDrawTiles>false</isDrawTiles><isDrawAnchors>false</isDrawAnchors><isDrawSides>false</isDrawSides><isDrawLanes>false</isDrawLanes></Config></Map>